mcp_youtube/__init__.py
mcp_youtube/mcp_youtube.py
iflow_mcp_adhikasp_mcp_youtube-0.1.0.dist-info/METADATA
iflow_mcp_adhikasp_mcp_youtube-0.1.0.dist-info/WHEEL
iflow_mcp_adhikasp_mcp_youtube-0.1.0.dist-info/entry_points.txt
iflow_mcp_adhikasp_mcp_youtube-0.1.0.dist-info/licenses/LICENSE
iflow_mcp_adhikasp_mcp_youtube-0.1.0.dist-info/RECORD
