Metadata-Version: 2.4
Name: iflow-mcp_adhikasp_mcp-youtube
Version: 0.1.0
Summary: MCP server for fetching YouTube transcripts
License-File: LICENSE
Requires-Dist: mcp
Requires-Dist: pydantic>=2.10.2
Requires-Dist: youtube-transcript-api
